ziso/__init__.py
ziso/zen.py
ziso/read/__init__.py
ziso/read/read.py
ziso/view/__init__.py
ziso/view/gray.py
ziso/view/rgb.py
ziso/view/view.py
eye_vision-0.0.2.dist-info/LICENSE
eye_vision-0.0.2.dist-info/LICENSE.txt
eye_vision-0.0.2.dist-info/METADATA
eye_vision-0.0.2.dist-info/WHEEL
eye_vision-0.0.2.dist-info/top_level.txt
eye_vision-0.0.2.dist-info/RECORD
