Metadata-Version: 2.1
Name: eye-vision
Version: 0.0.2
Summary: Computer Vision library that makes simple the new powerful.
Home-page: https://simbatmotsi.github.io/eye-vision/
Author: Simbarashe Timothy Motsi
Author-email: simbamotsi1@gmail.com
License: UNKNOWN
Platform: UNKNOWN
Classifier: Programming Language :: Python :: 3
Classifier: Intended Audience :: Developers
Classifier: Intended Audience :: Education
Classifier: Intended Audience :: Information Technology
Classifier: Intended Audience :: Science/Research
Classifier: License :: OSI Approved :: MIT License
Classifier: Operating System :: OS Independent
Classifier: Topic :: Scientific/Engineering
Classifier: Topic :: Scientific/Engineering :: Image Recognition
Classifier: Topic :: Software Development
Requires-Dist: opencv-python
Requires-Dist: matplotlib
